{
    "cells": [
        {
            "position": {
                "x": -7,
                "y": 1,
                "z": 0
            },
            "terrainType": "BasicGrass_0"
        },
        {
            "position": {
                "x": 4,
                "y": 1,
                "z": 0
            },
            "terrainType": "BasicGrass_1"
        },
        {
            "position": {
                "x": 5,
                "y": 1,
                "z": 0
            },
            "terrainType": "BasicGrass_1"
        },
        {
            "position": {
                "x": 6,
                "y": 1,
                "z": 0
            },
            "terrainType": "BasicGrass_1"
        },
        {
            "position": {
                "x": 7,
                "y": 1,
                "z": 0
            },
            "terrainType": "BasicGrass_1"
        },
        {
            "position": {
                "x": 8,
                "y": 1,
                "z": 0
            },
            "terrainType": "BasicGrass_1"
        },
        {
            "position": {
                "x": -6,
                "y": 2,
                "z": 0
            },
            "terrainType": "BasicGrass_1"
        },
        {
            "position": {
                "x": -5,
                "y": 2,
                "z": 0
            },
            "terrainType": "BasicGrass_1"
        },
        {
            "position": {
                "x": -4,
                "y": 2,
                "z": 0
            },
            "terrainType": "BasicGrass_1"
        },
        {
            "position": {
                "x": -3,
                "y": 2,
                "z": 0
            },
            "terrainType": "BasicGrass_1"
        },
        {
            "position": {
                "x": -2,
                "y": 2,
                "z": 0
            },
            "terrainType": "BasicGrass_1"
        },
        {
            "position": {
                "x": -1,
                "y": 2,
                "z": 0
            },
            "terrainType": "BasicGrass_1"
        },
        {
            "position": {
                "x": 0,
                "y": 2,
                "z": 0
            },
            "terrainType": "BasicGrass_1"
        },
        {
            "position": {
                "x": 1,
                "y": 2,
                "z": 0
            },
            "terrainType": "BasicGrass_1"
        },
        {
            "position": {
                "x": 2,
                "y": 2,
                "z": 0
            },
            "terrainType": "BasicGrass_1"
        },
        {
            "position": {
                "x": 3,
                "y": 2,
                "z": 0
            },
            "terrainType": "BasicGrass_1"
        }
    ]
}